zeroconf.py
zeroconf2-0.19.2.dist-info/DESCRIPTION.rst
zeroconf2-0.19.2.dist-info/METADATA
zeroconf2-0.19.2.dist-info/RECORD
zeroconf2-0.19.2.dist-info/WHEEL
zeroconf2-0.19.2.dist-info/metadata.json
zeroconf2-0.19.2.dist-info/top_level.txt
